[
    {
        "code": "01",
        "name": "Life_Of_Boris_-_Generation_Hardbass"  
    },
    {
        "code": "02",
        "name": "DJ_Blyatman_-_Babushka"  
    },
    {
        "code": "03",
        "name": "DJ_Blyatman_-_Gopnik"  
    },
    {
        "code": "04",
        "name": "Life_Of_Boris_-_No_Ruski_Pop"  
    },
    {
        "code": "05",
        "name": "Life_Of_Boris_-_Slav_King"  
    },
    {
        "code": "06",
        "name": "DJ_Blyatman_-_Vice_City"  
    },
    {
        "code": "07",
        "name": "DJ_Blyatman_-_Kalashnikov"  
    },
    {
        "code": "08",
        "name": "DJ_Blyatman_-_Kamaz"  
    },
    {
        "code": "09",
        "name": "Life_Of_Boris_-_Lada"  
    },
    {
        "code": "10",
        "name": "Life_Of_Boris_-_Parking_lot"  
    },
    {
        "code": "11",
        "name": "Life_Of_Boris_-_Red_Roubles"  
    }
]
